CTkBuilder/__init__.py
CTkBuilder/ctkbuilder.py
ctkbuilder-1.0.0.dist-info/LICENSE
ctkbuilder-1.0.0.dist-info/METADATA
ctkbuilder-1.0.0.dist-info/WHEEL
ctkbuilder-1.0.0.dist-info/top_level.txt
ctkbuilder-1.0.0.dist-info/RECORD
