Metadata-Version: 2.1
Name: ctkbuilder
Version: 1.0.0
Summary: A JSON-driven customtkinter GUI builder
Home-page: https://github.com/mst4cks/CTkBuilder
Author: mst4ck
Classifier: Programming Language :: Python :: 3
Classifier: License :: OSI Approved :: MIT License
Classifier: Operating System :: OS Independent
Requires-Python: >=3.11
License-File: LICENSE
Requires-Dist: customtkinter
Requires-Dist: hPyT
